exasol/python_extension_common/__init__.py
exasol/python_extension_common/cli/bucketfs_conn_object_cli.py
exasol/python_extension_common/cli/language_container_deployer_cli.py
exasol/python_extension_common/cli/std_options.py
exasol/python_extension_common/connections/bucketfs_location.py
exasol/python_extension_common/connections/pyexasol_connection.py
exasol/python_extension_common/deployment/__init__.py
exasol/python_extension_common/deployment/extract_validator.py
exasol/python_extension_common/deployment/language_container/flavor_base/build_steps.py
exasol/python_extension_common/deployment/language_container/flavor_base/dependencies/.gitignore
exasol/python_extension_common/deployment/language_container/flavor_base/dependencies/Dockerfile
exasol/python_extension_common/deployment/language_container/flavor_base/release/.gitignore
exasol/python_extension_common/deployment/language_container/flavor_base/release/Dockerfile
exasol/python_extension_common/deployment/language_container_builder.py
exasol/python_extension_common/deployment/language_container_deployer.py
exasol/python_extension_common/deployment/language_container_deployer_cli.py
exasol/python_extension_common/deployment/language_container_validator.py
exasol/python_extension_common/deployment/temp_schema.py
exasol/python_extension_common/py.typed
exasol_python_extension_common-0.10.0.dist-info/LICENSE
exasol_python_extension_common-0.10.0.dist-info/METADATA
exasol_python_extension_common-0.10.0.dist-info/WHEEL
exasol_python_extension_common-0.10.0.dist-info/RECORD
