Metadata-Version: 2.3
Name: exasol-python-extension-common
Version: 0.10.0
Summary: A collection of common utilities for Exasol extensions.
License: MIT
Author: Mikhail Beck
Author-email: mikhail.beck@exasol.com
Requires-Python: >=3.10,<4.0
Classifier: License :: OSI Approved :: MIT License
Classifier: Programming Language :: Python :: 3
Classifier: Programming Language :: Python :: 3.10
Classifier: Programming Language :: Python :: 3.11
Classifier: Programming Language :: Python :: 3.12
Classifier: Programming Language :: Python :: 3.13
Requires-Dist: click (>=8.1.7,<9.0.0)
Requires-Dist: exasol-bucketfs (>=0.10.0)
Requires-Dist: exasol-saas-api (>=1.1.0,<2)
Requires-Dist: exasol-script-languages-container-tool (>=1.0.0,<2.0.0)
Requires-Dist: pyexasol (>=0.25.0,<1.0.0)
Requires-Dist: requests (>=2.32.0)
Requires-Dist: tenacity (>=8.3.0,<9.0.0)
